README.rst
setup.py
aws_backup/__init__.py
aws_backup/compat.py
aws_backup/exceptions.py
aws_backup/parser.py
aws_backup/bin/__init__.py
aws_backup/bin/ec2.py
aws_backup/client/__init__.py
aws_backup/client/base.py
aws_backup/client/ec2.py
aws_backup/tests/__init__.py
aws_backup/tests/compat.py
aws_backup/tests/test_bin_ec2.py
aws_backup/tests/test_client_base.py
aws_backup/tests/test_client_ec2.py
aws_backup/tests/test_parser.py
aws_backup_client.egg-info/PKG-INFO
aws_backup_client.egg-info/SOURCES.txt
aws_backup_client.egg-info/dependency_links.txt
aws_backup_client.egg-info/entry_points.txt
aws_backup_client.egg-info/requires.txt
aws_backup_client.egg-info/top_level.txt