Metadata-Version: 1.1
Name: aws-backup-client
Version: 0.0.5
Summary: aws backup clients
Home-page: https://github.com/righ/aws-backup-client
Author: righ
Author-email: righ.m9@gmail.com
License: Apache License 2.0
Keywords: aws,backup,ec2,ami
Platform: UNKNOWN
Classifier: Environment :: Console
Classifier: Intended Audience :: System Administrators
Classifier: License :: OSI Approved :: Apache Software License
Classifier: Programming Language :: Python
Classifier: Topic :: Software Development
